cvmodule/__init__.py
cvmodule/test_data.py
cvmodule/utils.py
cvmodule/CV/__init__.py
cvmodule/CV/add_noise.py
cvmodule/CV/cv_utils.py
cvmodule/CV/image_correction.py
cvmodule/CV/open_pose.py
cvmodule/Classifier/__init__.py
cvmodule/Classifier/abc_main.py
cvmodule/Classifier/data.py
cvmodule/Classifier/main.py
cvmodule/Classifier/tfrecord.py
cvmodule/ConvModel/__init__.py
cvmodule/ConvModel/conv_utils.py
cvmodule/ConvModel/csp_net.py
cvmodule/ConvModel/eca_resnet.py
cvmodule/ConvModel/efficient_net.py
cvmodule/ConvModel/fpn_net.py
cvmodule/ConvModel/hr_net.py
cvmodule/ConvModel/panet.py
cvmodule/ConvModel/res_next.py
cvmodule/ConvModel/resnest.py
cvmodule/ConvModel/resnet_101.py
cvmodule/ConvModel/retina_net.py
cvmodule/ConvModel/se_net.py
cvmodule/ConvModel/sk_net.py
cvmodule/ConvModel/vov_net.py
cvmodule/ConvModel/encoder/__init__.py
cvmodule/ConvModel/encoder/mobilenet.py
cvmodule/ConvModel/encoder/resnet50.py
cvmodule/ConvModel/encoder/vgg16.py
cvmodule/ConvModel/torch_model/__init__.py
cvmodule/ConvModel/torch_model/eca_resnet.py
cvmodule/ConvModel/torch_model/vov_net.py
cvmodule/Detection/__init__.py
cvmodule/Detection/losses.py
cvmodule/Detection/models/__init__.py
cvmodule/Detection/utils/__init__.py
cvmodule/Detection/utils/draw_boxes.py
cvmodule/GAN/__init__.py
cvmodule/GAN/gan_loss.py
cvmodule/GCN/__init__.py
cvmodule/GCN/models/__init__.py
cvmodule/HumeanPoseEstimate/__init__.py
cvmodule/HumeanPoseEstimate/loss.py
cvmodule/HumeanPoseEstimate/train.py
cvmodule/HumeanPoseEstimate/data/__init__.py
cvmodule/HumeanPoseEstimate/data/coco_config.py
cvmodule/HumeanPoseEstimate/data/coco_data.py
cvmodule/HumeanPoseEstimate/data/show_info.py
cvmodule/HumeanPoseEstimate/models/HRNet.py
cvmodule/HumeanPoseEstimate/models/__init__.py
cvmodule/Module/CBAM.py
cvmodule/Module/__init__.py
cvmodule/Module/asff.py
cvmodule/Module/attention.py
cvmodule/Module/cbam_block.py
cvmodule/Module/csp.py
cvmodule/Module/eca.py
cvmodule/Module/get_norm.py
cvmodule/Module/grop_conv.py
cvmodule-0.0.5.dist-info/LICENSE.md
cvmodule-0.0.5.dist-info/METADATA
cvmodule-0.0.5.dist-info/WHEEL
cvmodule-0.0.5.dist-info/top_level.txt
cvmodule-0.0.5.dist-info/RECORD
