Metadata-Version: 2.1
Name: cvmodule
Version: 0.0.5
Summary: modules related to deep learning in computer vision
Home-page: https://github.com/YuHe0108/cvmodule
Author: YuHe
Author-email: 1941254847@qq.com
License: UNKNOWN
Platform: UNKNOWN
Classifier: Programming Language :: Python :: 3
Classifier: License :: OSI Approved :: MIT License
Classifier: Operating System :: OS Independent
Requires-Python: >=3.6
License-File: LICENSE.md
